libname/__init__.py
libname/test_pip_install.py
matrixmultiplier123-0.0.1.dist-info/METADATA
matrixmultiplier123-0.0.1.dist-info/WHEEL
matrixmultiplier123-0.0.1.dist-info/top_level.txt
matrixmultiplier123-0.0.1.dist-info/RECORD
