Metadata-Version: 2.1
Name: matrixmultiplier123
Version: 0.0.1
Summary: Basic matrix multiplier
Home-page: UNKNOWN
Author: Mike Terekhov
Author-email: <terekhovhd@gmail.com>
License: UNKNOWN
Keywords: matrix,multiplier
Platform: UNKNOWN
Classifier: Development Status :: 1 - Planning
Classifier: Intended Audience :: Developers
Classifier: Programming Language :: Python :: 3
Classifier: Operating System :: Unix
Classifier: Operating System :: MacOS :: MacOS X
Classifier: Operating System :: Microsoft :: Windows
Requires-Dist: numpy
